tvdb_rss/__init__.py
tvdb_rss/__main__.py
tvdb_rss/config.py
tvdb_rss/data_classes.py
tvdb_rss/rss.py
tvdb_rss/setup_logger.py
tvdb_rss/tvdb.py
tvdb_rss-0.0.13.dist-info/LICENSE
tvdb_rss-0.0.13.dist-info/METADATA
tvdb_rss-0.0.13.dist-info/WHEEL
tvdb_rss-0.0.13.dist-info/top_level.txt
tvdb_rss-0.0.13.dist-info/RECORD
