Metadata-Version: 2.1
Name: tvdb-rss
Version: 0.0.13
Summary: UNKNOWN
Home-page: https://github.com/csm10495/tvdb_rss
Author: csm10495
Author-email: csm10495@gmail.com
License: MIT License
Platform: UNKNOWN
Classifier: Intended Audience :: Developers
Classifier: Natural Language :: English
Classifier: Operating System :: POSIX
Classifier: Operating System :: Microsoft :: Windows
Classifier: Programming Language :: Python
Classifier: Programming Language :: Python :: 3
Classifier: Programming Language :: Python :: 3.7
Requires-Python: >=3.7
Requires-Dist: csmlog
Requires-Dist: requests
Requires-Dist: feedgen
